{
  "Version": 1,
  "Name": "eu-ES",
  "CurrencyDecimalDigits": 2,
  "CurrencyGroupSizes": [
    3
  ],
  "CurrencyNegativePattern": 8,
  "CurrencySymbol": "€",
  "DigitSubstitution": 1,
  "NaNSymbol": "EdZ",
  "NegativeInfinitySymbol": "-Infinitu",
  "NumberDecimalDigits": 2,
  "PercentDecimalDigits": 2,
  "PercentDecimalSeparator": ",",
  "PercentGroupSeparator": ".",
  "PercentGroupSizes": [
    3
  ],
  "PercentNegativePattern": 0,
  "PercentPositivePattern": 0,
  "PercentSymbol": "%",
  "PerMilleSymbol": "‰",
  "PositiveInfinitySymbol": "Infinitu",
  "ShortestDayNames": [
    "ig",
    "al",
    "as",
    "az",
    "og",
    "or",
    "lr"
  ],
  "FullDateTimePattern": "dddd, yyyy.'eko' MMMM'k 'd H:mm:ss",
  "LongDatePattern": "dddd, yyyy.'eko' MMMM'k 'd",
  "LongTimePattern": "H:mm:ss",
  "ShortDatePattern": "yyyy/MM/dd",
  "ShortTimePattern": "HH:mm",
  "NativeCalendarName": "egutegi gregoriotarra",
  "CurrencyPositivePattern": 3,
  "CurrencyPrecedesNumber": false,
  "NativeDigits": [
    "0",
    "1",
    "2",
    "3",
    "4",
    "5",
    "6",
    "7",
    "8",
    "9"
  ],
  "NegativeSign": "-",
  "PositiveSign": "+",
  "NumberGroupSizes": [
    3
  ],
  "NumberNegativePattern": 1,
  "NumberGroupSeparator": ".",
  "NumberDecimalSeparator": ",",
  "CurrencyGroupSeparator": ".",
  "CurrencyDecimalSeparator": ",",
  "DateSeparator": "/",
  "TimeSeparator": ":",
  "AMDesignator": "",
  "PMDesignator": "",
  "DateTimePatterns": [
    "yyyy/MM/dd",
    "yyyy/M/dd",
    "yyyy/M/d",
    "yyyy/MM/d",
    "yyyy-MM-dd",
    "yyyy-M-dd",
    "yyyy-M-d",
    "yyyy-MM-d",
    "dddd, yyyy.'eko' MMMM'k 'd",
    "dddd, yyyy.'eko' MMMM'k 'd HH:mm",
    "dddd, yyyy.'eko' MMMM'k 'd H:mm:ss",
    "dddd, yyyy.'eko' MMMM'k 'd HH:mm:ss",
    "dddd, yyyy.'eko' MMMM'k 'd HH'H'mm'\\''ss'\\'\\''",
    "yyyy/MM/dd HH:mm",
    "yyyy-MM-dd HH:mm",
    "yyyy/MM/dd H:mm:ss",
    "yyyy/MM/dd HH:mm:ss",
    "yyyy/MM/dd HH'H'mm'\\''ss'\\'\\''",
    "yyyy-MM-dd H:mm:ss",
    "yyyy-MM-dd HH:mm:ss",
    "yyyy-MM-dd HH'H'mm'\\''ss'\\'\\''",
    "MMMM dd",
    "MMMM dd",
    "yyyy'-'MM'-'dd'T'HH':'mm':'ss.fffffffK",
    "yyyy'-'MM'-'dd'T'HH':'mm':'ss.fffffffK",
    "ddd, dd MMM yyyy HH':'mm':'ss 'GMT'",
    "ddd, dd MMM yyyy HH':'mm':'ss 'GMT'",
    "yyyy'-'MM'-'dd'T'HH':'mm':'ss",
    "HH:mm",
    "H:mm",
    "H:mm:ss",
    "HH:mm:ss",
    "HH'H'mm'\\''ss'\\'\\''",
    "H'H'mm'\\''ss'\\'\\''",
    "yyyy'-'MM'-'dd HH':'mm':'ss'Z'",
    "dddd, yyyy.'eko' MMMM'k 'd H:mm:ss",
    "dddd, yyyy.'eko' MMMM'k 'd HH:mm:ss",
    "dddd, yyyy.'eko' MMMM'k 'd HH'H'mm'\\''ss'\\'\\''",
    "yyyy.'eko' MMMM",
    "yyyy.'eko' MMMM"
  ],
  "AbbreviatedMonthNames": [
    "urt.",
    "ots.",
    "mar.",
    "api.",
    "mai.",
    "eka.",
    "uzt.",
    "abu.",
    "ira.",
    "urr.",
    "aza.",
    "abe.",
    ""
  ],
  "AbbreviatedMonthGenitiveNames": [
    "urt.",
    "ots.",
    "mar.",
    "api.",
    "mai.",
    "eka.",
    "uzt.",
    "abu.",
    "ira.",
    "urr.",
    "aza.",
    "abe.",
    ""
  ],
  "MonthNames": [
    "urtarrila",
    "otsaila",
    "martxoa",
    "apirila",
    "maiatza",
    "ekaina",
    "uztaila",
    "abuztua",
    "iraila",
    "urria",
    "azaroa",
    "abendua",
    ""
  ],
  "MonthGenitiveNames": [
    "urtarrila",
    "otsaila",
    "martxoa",
    "apirila",
    "maiatza",
    "ekaina",
    "uztaila",
    "abuztua",
    "iraila",
    "urria",
    "azaroa",
    "abendua",
    ""
  ],
  "AbbreviatedDayNames": [
    "ig.",
    "al.",
    "as.",
    "az.",
    "og.",
    "or.",
    "lr."
  ],
  "DayNames": [
    "igandea",
    "astelehena",
    "asteartea",
    "asteazkena",
    "osteguna",
    "ostirala",
    "larunbata"
  ],
  "EraNames": [
    "d.C."
  ]
}