{
  "Version": 1,
  "Name": "dz-BT",
  "CurrencyDecimalDigits": 2,
  "CurrencyGroupSizes": [
    3,
    2
  ],
  "CurrencyNegativePattern": 1,
  "CurrencySymbol": "Nu.",
  "DigitSubstitution": 2,
  "NaNSymbol": "NaN",
  "NegativeInfinitySymbol": "-∞",
  "NumberDecimalDigits": 2,
  "PercentDecimalDigits": 2,
  "PercentDecimalSeparator": ".",
  "PercentGroupSeparator": ",",
  "PercentGroupSizes": [
    3,
    2
  ],
  "PercentNegativePattern": 0,
  "PercentPositivePattern": 0,
  "PercentSymbol": "%",
  "PerMilleSymbol": "‰",
  "PositiveInfinitySymbol": "∞",
  "ShortestDayNames": [
    "ཟླ་",
    "མིར་",
    "ལྷག་",
    "ཕུར་",
    "སངས་",
    "སྤེན་",
    "ཉི་"
  ],
  "FullDateTimePattern": "dddd, སྤྱི་ལོ་yyyy MMMM ཚེས་dd ཆུ་ཚོད་h:mm:ss tt",
  "LongDatePattern": "dddd, སྤྱི་ལོ་yyyy MMMM ཚེས་dd",
  "LongTimePattern": "ཆུ་ཚོད་h:mm:ss tt",
  "ShortDatePattern": "yyyy-MM-dd",
  "ShortTimePattern": "ཆུ་ཚོད་ h སྐར་མ་ mm tt",
  "NativeCalendarName": "གྲེག་གོ་རི་ཡཱན་ཟླ་ཐོ",
  "CurrencyPositivePattern": 0,
  "CurrencyPrecedesNumber": true,
  "NativeDigits": [
    "༠",
    "༡",
    "༢",
    "༣",
    "༤",
    "༥",
    "༦",
    "༧",
    "༨",
    "༩"
  ],
  "NegativeSign": "-",
  "PositiveSign": "+",
  "NumberGroupSizes": [
    3,
    2
  ],
  "NumberNegativePattern": 1,
  "NumberGroupSeparator": ",",
  "NumberDecimalSeparator": ".",
  "CurrencyGroupSeparator": ",",
  "CurrencyDecimalSeparator": ".",
  "DateSeparator": "-",
  "TimeSeparator": ":",
  "AMDesignator": "སྔ་ཆ་",
  "PMDesignator": "ཕྱི་ཆ་",
  "DateTimePatterns": [
    "yyyy-MM-dd",
    "yyyy-M-dd",
    "yyyy-M-d",
    "yyyy-MM-d",
    "སྤྱི་ལོ་yyyy ཟླ་MMM ཚེས་dd",
    "སྤྱི་ལོ་yyyy ཟླ་MMM ཚེས་d",
    "dddd, སྤྱི་ལོ་yyyy MMMM ཚེས་dd",
    "dddd, སྤྱི་ལོ་yyyy MMMM ཚེས་d",
    "སྤྱི་ལོ་yyyy MMMM ཚེས་ dd",
    "སྤྱི་ལོ་yyyy MMMM ཚེས་ d",
    "dddd, སྤྱི་ལོ་yyyy MMMM ཚེས་dd ཆུ་ཚོད་ h སྐར་མ་ mm tt",
    "dddd, སྤྱི་ལོ་yyyy MMMM ཚེས་dd HH:mm",
    "སྤྱི་ལོ་yyyy MMMM ཚེས་ dd ཆུ་ཚོད་ h སྐར་མ་ mm tt",
    "སྤྱི་ལོ་yyyy MMMM ཚེས་ dd HH:mm",
    "dddd, སྤྱི་ལོ་yyyy MMMM ཚེས་dd ཆུ་ཚོད་h:mm:ss tt",
    "dddd, སྤྱི་ལོ་yyyy MMMM ཚེས་dd HH:mm:ss",
    "སྤྱི་ལོ་yyyy MMMM ཚེས་ dd ཆུ་ཚོད་h:mm:ss tt",
    "སྤྱི་ལོ་yyyy MMMM ཚེས་ dd HH:mm:ss",
    "yyyy-MM-dd ཆུ་ཚོད་ h སྐར་མ་ mm tt",
    "yyyy-MM-dd HH:mm",
    "སྤྱི་ལོ་yyyy ཟླ་MMM ཚེས་dd ཆུ་ཚོད་ h སྐར་མ་ mm tt",
    "སྤྱི་ལོ་yyyy ཟླ་MMM ཚེས་dd HH:mm",
    "yyyy-MM-dd ཆུ་ཚོད་h:mm:ss tt",
    "yyyy-MM-dd HH:mm:ss",
    "སྤྱི་ལོ་yyyy ཟླ་MMM ཚེས་dd ཆུ་ཚོད་h:mm:ss tt",
    "སྤྱི་ལོ་yyyy ཟླ་MMM ཚེས་dd HH:mm:ss",
    "སྤྱི་MMMM ཚེ་d",
    "སྤྱི་MMMM ཚེ་d",
    "yyyy'-'MM'-'dd'T'HH':'mm':'ss.fffffffK",
    "yyyy'-'MM'-'dd'T'HH':'mm':'ss.fffffffK",
    "ddd, dd MMM yyyy HH':'mm':'ss 'GMT'",
    "ddd, dd MMM yyyy HH':'mm':'ss 'GMT'",
    "yyyy'-'MM'-'dd'T'HH':'mm':'ss",
    "ཆུ་ཚོད་ h སྐར་མ་ mm tt",
    "HH:mm",
    "H:mm",
    "ཆུ་ཚོད་h:mm:ss tt",
    "HH:mm:ss",
    "H:mm:ss",
    "yyyy'-'MM'-'dd HH':'mm':'ss'Z'",
    "dddd, སྤྱི་ལོ་yyyy MMMM ཚེས་dd ཆུ་ཚོད་h:mm:ss tt",
    "dddd, སྤྱི་ལོ་yyyy MMMM ཚེས་dd HH:mm:ss",
    "སྤྱི་ལོ་yyyy MMMM ཚེས་ dd ཆུ་ཚོད་h:mm:ss tt",
    "སྤྱི་ལོ་yyyy MMMM ཚེས་ dd HH:mm:ss",
    "yyyy སྤྱི་ཟླ་MMMM",
    "yyyy སྤྱི་ཟླ་MMMM"
  ],
  "AbbreviatedMonthNames": [
    "ཟླ་༡",
    "ཟླ་༢",
    "ཟླ་༣",
    "ཟླ་༤",
    "ཟླ་༥",
    "ཟླ་༦",
    "ཟླ་༧",
    "ཟླ་༨",
    "ཟླ་༩",
    "ཟླ་༡༠",
    "ཟླ་༡༡",
    "ཟླ་༡༢",
    ""
  ],
  "AbbreviatedMonthGenitiveNames": [
    "༡",
    "༢",
    "༣",
    "༤",
    "༥",
    "༦",
    "༧",
    "༨",
    "༩",
    "༡༠",
    "༡༡",
    "12",
    ""
  ],
  "MonthNames": [
    "སྤྱི་ཟླ་དངཔ་",
    "སྤྱི་ཟླ་གཉིས་པ་",
    "སྤྱི་ཟླ་གསུམ་པ་",
    "སྤྱི་ཟླ་བཞི་པ",
    "སྤྱི་ཟླ་ལྔ་པ་",
    "སྤྱི་ཟླ་དྲུག་པ",
    "སྤྱི་ཟླ་བདུན་པ་",
    "སྤྱི་ཟླ་བརྒྱད་པ་",
    "སྤྱི་ཟླ་དགུ་པ་",
    "སྤྱི་ཟླ་བཅུ་པ་",
    "སྤྱི་ཟླ་བཅུ་གཅིག་པ་",
    "སྤྱི་ཟླ་བཅུ་གཉིས་པ་",
    ""
  ],
  "MonthGenitiveNames": [
    "ཟླ་དངཔ་",
    "ཟླ་གཉིས་པ་",
    "ཟླ་གསུམ་པ་",
    "ཟླ་བཞི་པ་",
    "ཟླ་ལྔ་པ་",
    "ཟླ་དྲུག་པ",
    "ཟླ་བདུན་པ་",
    "ཟླ་བརྒྱད་པ་",
    "ཟླ་དགུ་པ་",
    "ཟླ་བཅུ་པ་",
    "ཟླ་བཅུ་གཅིག་པ་",
    "ཟླ་བཅུ་གཉིས་པ་",
    ""
  ],
  "AbbreviatedDayNames": [
    "ཟླ་",
    "མིར་",
    "ལྷག་",
    "ཕུར་",
    "སངས་",
    "སྤེན་",
    "ཉི་"
  ],
  "DayNames": [
    "གཟའ་ཟླ་བ་",
    "གཟའ་མིག་དམར་",
    "གཟའ་ལྷག་པ་",
    "གཟའ་ཕུར་བུ་",
    "གཟའ་པ་སངས་",
    "གཟའ་སྤེན་པ་",
    "གཟའ་ཉི་མ་"
  ],
  "EraNames": [
    "CE"
  ]
}