{
  "Version": 1,
  "Name": "ps-AF",
  "CurrencyDecimalDigits": 0,
  "CurrencyGroupSizes": [
    3
  ],
  "CurrencyNegativePattern": 8,
  "CurrencySymbol": "؋",
  "DigitSubstitution": 2,
  "NaNSymbol": "NaN",
  "NegativeInfinitySymbol": "-∞",
  "NumberDecimalDigits": 2,
  "PercentDecimalDigits": 2,
  "PercentDecimalSeparator": ",",
  "PercentGroupSeparator": ".",
  "PercentGroupSizes": [
    3
  ],
  "PercentNegativePattern": 1,
  "PercentPositivePattern": 1,
  "PercentSymbol": "%",
  "PerMilleSymbol": "‰",
  "PositiveInfinitySymbol": "∞",
  "ShortestDayNames": [
    "ح",
    "ن",
    "ث",
    "ر",
    "خ",
    "ج",
    "س"
  ],
  "FullDateTimePattern": "dd/MM/yyyy h:mm:ss tt",
  "LongDatePattern": "dd/MM/yyyy",
  "LongTimePattern": "h:mm:ss tt",
  "ShortDatePattern": "dd/MM/yy",
  "ShortTimePattern": "h:mm tt",
  "NativeCalendarName": "Persian Calendar",
  "CurrencyPositivePattern": 3,
  "CurrencyPrecedesNumber": false,
  "NativeDigits": [
    "٠",
    "١",
    "٢",
    "٣",
    "٤",
    "٥",
    "٦",
    "٧",
    "٨",
    "٩"
  ],
  "NegativeSign": "-",
  "PositiveSign": "+",
  "NumberGroupSizes": [
    3
  ],
  "NumberNegativePattern": 1,
  "NumberGroupSeparator": ".",
  "NumberDecimalSeparator": ",",
  "CurrencyGroupSeparator": "٬",
  "CurrencyDecimalSeparator": "٫",
  "DateSeparator": "/",
  "TimeSeparator": ":",
  "AMDesignator": "غ.م",
  "PMDesignator": "غ.و",
  "DateTimePatterns": [
    "dd/MM/yy",
    "dd/M/yy",
    "d/M/yy",
    "d/MM/yy",
    "dd/MM/yyyy",
    "dd/M/yyyy",
    "d/M/yyyy",
    "d/MM/yyyy",
    "dd/MM/yyyy",
    "dd/MMMM/yyyy",
    "d/MMMM/yyyy",
    "dddd, dd MMMM, yyyy",
    "dddd, d MMMM, yyyy",
    "dd/MM/yyyy 'هـ'",
    "dd/M/yyyy 'هـ'",
    "d/M/yyyy 'هـ'",
    "d/MM/yyyy 'هـ'",
    "dd/MM/yyyy h:mm tt",
    "dd/MM/yyyy H:mm",
    "dd/MMMM/yyyy h:mm tt",
    "dd/MMMM/yyyy H:mm",
    "dddd, dd MMMM, yyyy h:mm tt",
    "dddd, dd MMMM, yyyy H:mm",
    "dd/MM/yyyy 'هـ' h:mm tt",
    "dd/MM/yyyy 'هـ' H:mm",
    "dd/MM/yyyy h:mm:ss tt",
    "dd/MM/yyyy H:mm:ss",
    "dd/MMMM/yyyy h:mm:ss tt",
    "dd/MMMM/yyyy H:mm:ss",
    "dddd, dd MMMM, yyyy h:mm:ss tt",
    "dddd, dd MMMM, yyyy H:mm:ss",
    "dd/MM/yyyy 'هـ' h:mm:ss tt",
    "dd/MM/yyyy 'هـ' H:mm:ss",
    "dd/MM/yy h:mm tt",
    "dd/MM/yy H:mm",
    "dd/MM/yyyy h:mm tt",
    "dd/MM/yyyy H:mm",
    "dd/MM/yy h:mm:ss tt",
    "dd/MM/yy H:mm:ss",
    "dd/MM/yyyy h:mm:ss tt",
    "dd/MM/yyyy H:mm:ss",
    "dd MMMM",
    "dd MMMM",
    "yyyy'-'MM'-'dd'T'HH':'mm':'ss.fffffffK",
    "yyyy'-'MM'-'dd'T'HH':'mm':'ss.fffffffK",
    "ddd, dd MMM yyyy HH':'mm':'ss 'GMT'",
    "ddd, dd MMM yyyy HH':'mm':'ss 'GMT'",
    "yyyy'-'MM'-'dd'T'HH':'mm':'ss",
    "h:mm tt",
    "H:mm",
    "h:mm:ss tt",
    "H:mm:ss",
    "yyyy'-'MM'-'dd HH':'mm':'ss'Z'",
    "dd/MM/yyyy h:mm:ss tt",
    "dd/MM/yyyy H:mm:ss",
    "dd/MMMM/yyyy h:mm:ss tt",
    "dd/MMMM/yyyy H:mm:ss",
    "dddd, dd MMMM, yyyy h:mm:ss tt",
    "dddd, dd MMMM, yyyy H:mm:ss",
    "dd/MM/yyyy 'هـ' h:mm:ss tt",
    "dd/MM/yyyy 'هـ' H:mm:ss",
    "MMMM, yyyy",
    "MMMM, yyyy"
  ],
  "AbbreviatedMonthNames": [
    "محرم",
    "صفر",
    "ربيع الأول",
    "ربيع الثاني",
    "جمادى الأولى",
    "جمادى الثانية",
    "رجب",
    "شعبان",
    "رمضان",
    "شوال",
    "ذو القعدة",
    "ذو الحجة",
    ""
  ],
  "AbbreviatedMonthGenitiveNames": [
    "محرم",
    "صفر",
    "ربيع الأول",
    "ربيع الثاني",
    "جمادى الأولى",
    "جمادى الثانية",
    "رجب",
    "شعبان",
    "رمضان",
    "شوال",
    "ذو القعدة",
    "ذو الحجة",
    ""
  ],
  "MonthNames": [
    "محرم",
    "صفر",
    "ربيع الأول",
    "ربيع الثاني",
    "جمادى الأولى",
    "جمادى الثانية",
    "رجب",
    "شعبان",
    "رمضان",
    "شوال",
    "ذو القعدة",
    "ذو الحجة",
    ""
  ],
  "MonthGenitiveNames": [
    "محرم",
    "صفر",
    "ربيع الأول",
    "ربيع الثاني",
    "جمادى الأولى",
    "جمادى الثانية",
    "رجب",
    "شعبان",
    "رمضان",
    "شوال",
    "ذو القعدة",
    "ذو الحجة",
    ""
  ],
  "AbbreviatedDayNames": [
    "الأحد",
    "الإثنين",
    "الثلاثاء",
    "الأربعاء",
    "الخميس",
    "الجمعة",
    "السبت"
  ],
  "DayNames": [
    "الأحد",
    "الإثنين",
    "الثلاثاء",
    "الأربعاء",
    "الخميس",
    "الجمعة",
    "السبت"
  ],
  "EraNames": [
    "بعد الهجرة"
  ]
}